zetch-0.0.16.dist-info/METADATA
zetch-0.0.16.dist-info/WHEEL
zetch-0.0.16.dist-info/entry_points.txt
zetch-0.0.16.dist-info/license_files/LICENSE.md
zetch-0.0.16.dist-info/license_files/LICENSE.zetch.md
zetch/py.typed
zetch/rust-toolchain.toml
zetch/utils.pyi
zetch/_yaml.py
zetch/__init__.py
zetch/__init__.pyi
zetch/_rs.cp310-win32.pyd
zetch-0.0.16.dist-info/RECORD
