Metadata-Version: 2.1
Name: zetch
Version: 0.0.16
Classifier: Development Status :: 3 - Alpha
Classifier: Intended Audience :: Developers
Classifier: Topic :: Software Development
Classifier: Typing :: Typed
Classifier: Operating System :: POSIX :: Linux
Classifier: Operating System :: Microsoft :: Windows
Classifier: Operating System :: MacOS
Classifier: Programming Language :: Python
Classifier: Programming Language :: Python :: Implementation :: CPython
Classifier: Programming Language :: Python :: 3
Classifier: Programming Language :: Python :: 3 :: Only
Classifier: Programming Language :: Python :: 3.8
Classifier: Programming Language :: Python :: 3.9
Classifier: Programming Language :: Python :: 3.10
Classifier: Programming Language :: Python :: 3.11
Classifier: Programming Language :: Python :: 3.12
Classifier: Programming Language :: Rust
Classifier: License :: OSI Approved
Requires-Dist: ruamel.yaml >=0.18.0, <=0.19.0
License-File: LICENSE.md
License-File: LICENSE.zetch.md
Summary: In-place, continuous templater.
Author-email: Zachary Stucke <zakstucke@gmail.com>
License: MIT
Requires-Python: >=3.8
Project-URL: Sourcecode, https://github.com/zakstucke/zetch
Project-URL: Documentation, https://zakstucke.github.io/zetch
